cabot_alert_twilio/__init__.py
cabot_alert_twilio/models.py
cabot_alert_twilio/urls.py
cabot_alert_twilio/views.py
cabot_alert_twilio/migrations/0001_initial.py
cabot_alert_twilio/migrations/__init__.py
cabot_alert_twilio-1.3.3.dist-info/DESCRIPTION.rst
cabot_alert_twilio-1.3.3.dist-info/METADATA
cabot_alert_twilio-1.3.3.dist-info/RECORD
cabot_alert_twilio-1.3.3.dist-info/WHEEL
cabot_alert_twilio-1.3.3.dist-info/metadata.json
cabot_alert_twilio-1.3.3.dist-info/top_level.txt
