Metadata-Version: 2.0
Name: cabot-alert-twilio
Version: 1.3.3
Summary: A twilio alert plugin for Cabot by Arachnys
Home-page: http://cabotapp.com
Author: Arachnys
Author-email: info@arachnys.org
License: UNKNOWN
Download-URL: https://github.com/cabotapp/cabot-alert-twilio/archive/1.3.1.zip
Platform: UNKNOWN
